odoo/addons/partner_disable_gravatar/README.rst
odoo/addons/partner_disable_gravatar/__init__.py
odoo/addons/partner_disable_gravatar/__manifest__.py
odoo/addons/partner_disable_gravatar/i18n/de.po
odoo/addons/partner_disable_gravatar/i18n/fr.po
odoo/addons/partner_disable_gravatar/i18n/it.po
odoo/addons/partner_disable_gravatar/i18n/partner_disable_gravatar.pot
odoo/addons/partner_disable_gravatar/models/__init__.py
odoo/addons/partner_disable_gravatar/models/res_partner.py
odoo/addons/partner_disable_gravatar/readme/CONTRIBUTORS.md
odoo/addons/partner_disable_gravatar/readme/DESCRIPTION.md
odoo/addons/partner_disable_gravatar/static/description/icon.png
odoo/addons/partner_disable_gravatar/static/description/index.html
odoo/addons/partner_disable_gravatar/tests/__init__.py
odoo/addons/partner_disable_gravatar/tests/test_partner_disable_gravatar.py
odoo_addon_partner_disable_gravatar-18.0.1.0.0.2.dist-info/METADATA
odoo_addon_partner_disable_gravatar-18.0.1.0.0.2.dist-info/WHEEL
odoo_addon_partner_disable_gravatar-18.0.1.0.0.2.dist-info/top_level.txt
odoo_addon_partner_disable_gravatar-18.0.1.0.0.2.dist-info/RECORD
